predicate/__init__.py
predicate/all_predicate.py
predicate/always_false_predicate.py
predicate/always_true_predicate.py
predicate/any_predicate.py
predicate/comp_predicate.py
predicate/count_predicate.py
predicate/dict_of_predicate.py
predicate/eq_predicate.py
predicate/explain.py
predicate/fn_predicate.py
predicate/ge_predicate.py
predicate/gt_predicate.py
predicate/has_key_predicate.py
predicate/has_length_predicate.py
predicate/has_path_predicate.py
predicate/helpers.py
predicate/implies.py
predicate/implies_predicate.py
predicate/in_predicate.py
predicate/in_predicate_predicate.py
predicate/ip_address_predicates.py
predicate/is_callable_predicate.py
predicate/is_falsy_predicate.py
predicate/is_instance_predicate.py
predicate/is_lambda_predicate.py
predicate/is_none_predicate.py
predicate/is_not_none_predicate.py
predicate/is_predicate_of_p.py
predicate/is_subclass_predicate.py
predicate/is_truthy_predicate.py
predicate/lazy_predicate.py
predicate/le_predicate.py
predicate/list_of_predicate.py
predicate/lt_predicate.py
predicate/match_predicate.py
predicate/named_predicate.py
predicate/ne_predicate.py
predicate/negate.py
predicate/not_in_predicate.py
predicate/parser.py
predicate/predicate.py
predicate/property_predicate.py
predicate/range_predicate.py
predicate/regex_predicate.py
predicate/root_predicate.py
predicate/set_of_predicate.py
predicate/set_predicates.py
predicate/standard_predicates.py
predicate/str_predicates.py
predicate/tee_predicate.py
predicate/this_predicate.py
predicate/truth_table.py
predicate/tuple_of_predicate.py
predicate/constructor/__init__.py
predicate/constructor/construct.py
predicate/constructor/helpers.py
predicate/constructor/mutate.py
predicate/formatter/__init__.py
predicate/formatter/format_dot.py
predicate/formatter/format_json.py
predicate/formatter/format_latex.py
predicate/formatter/helpers.py
predicate/generator/__init__.py
predicate/generator/generate_false.py
predicate/generator/generate_predicate.py
py_predicate-1.3.dist-info/licenses/LICENSE
py_predicate-1.3.dist-info/WHEEL
py_predicate-1.3.dist-info/METADATA
py_predicate-1.3.dist-info/RECORD
