Metadata-Version: 2.4
Name: py_predicate
Version: 1.3
Summary: Module to create composable predicates
Author-email: Maurits Rijk <maurits.rijk@gmail.com>
Requires-Python: >=3.10
Classifier: Intended Audience :: Information Technology
Classifier: Intended Audience :: Developers
Classifier: Operating System :: OS Independent
Classifier: Programming Language :: Python :: 3
Classifier: Programming Language :: Python
Classifier: Topic :: Internet
Classifier: Topic :: Software Development :: Libraries :: Python Modules
Classifier: Topic :: Software Development :: Libraries
Classifier: Topic :: Software Development
Classifier: Typing :: Typed
Classifier: Development Status :: 5 - Production/Stable
Classifier: Environment :: Web Environment
Classifier: License :: OSI Approved :: MIT License
Classifier: Programming Language :: Python :: 3 :: Only
Classifier: Programming Language :: Python :: 3.13
Classifier: Programming Language :: Python :: 3.12
License-File: LICENSE
Requires-Dist: exrex
Requires-Dist: graphviz
Requires-Dist: lark
Requires-Dist: more-itertools
Requires-Dist: typer
Requires-Dist: bumpversion ; extra == "dev"
Requires-Dist: jsonschema ; extra == "dev"
Requires-Dist: pre-commit ; extra == "dev"
Requires-Dist: black ; extra == "test"
Requires-Dist: mypy ; extra == "test"
Requires-Dist: mypy_extensions ; extra == "test"
Requires-Dist: pytest ; extra == "test"
Requires-Dist: pytest-benchmark ; extra == "test"
Requires-Dist: pytest-cov ; extra == "test"
Requires-Dist: ruff ; extra == "test"
Project-URL: Documentation, https://mrijk.github.io/py-predicate/
Project-URL: Source, https://github.com/mrijk/py-predicate
Provides-Extra: dev
Provides-Extra: test
